check_driver/__init__.py
check_driver-1.0.0.dist-info/LICENSE
check_driver-1.0.0.dist-info/METADATA
check_driver-1.0.0.dist-info/WHEEL
check_driver-1.0.0.dist-info/top_level.txt
check_driver-1.0.0.dist-info/RECORD
