Metadata-Version: 2.1
Name: check-driver
Version: 1.0.0
Summary: A small check driver
Home-page: UNKNOWN
Author: Marcelo Tavares
Author-email: contato@mtavaresc.com.br
License: MIT
Platform: UNKNOWN
Classifier: Programming Language :: Python :: 3
Classifier: License :: OSI Approved :: MIT License
Classifier: Operating System :: OS Independent
Requires-Python: >=3.6
Requires-Dist: requests
